{
	"info": {
		"_postman_id": "d6025987-6fd8-4123-941d-13f1947142a5",
		"name": "Favourites",
		"schema": "https://schema.getpostman.com/json/collection/v2.1.0/collection.json",
		"_exporter_id": "16150599"
	},
	"item": [
		{
			"name": "Favourites",
			"request": {
				"method": "GET",
				"header": [],
				"url": {
					"raw": "http://127.0.0.1:8004/favourites",
					"protocol": "http",
					"host": [
						"127",
						"0",
						"0",
						"1"
					],
					"port": "8004",
					"path": [
						"favourites"
					]
				}
			},
			"response": []
		},
		{
			"name": "Add to favs",
			"request": {
				"method": "POST",
				"header": [],
				"url": {
					"raw": "http://127.0.0.1:8004/favourites/4",
					"protocol": "http",
					"host": [
						"127",
						"0",
						"0",
						"1"
					],
					"port": "8004",
					"path": [
						"favourites",
						"4"
					]
				}
			},
			"response": []
		},
		{
			"name": "Check if in favs",
			"request": {
				"method": "GET",
				"header": [],
				"url": {
					"raw": "http://127.0.0.1:8004/favourites/check/4",
					"protocol": "http",
					"host": [
						"127",
						"0",
						"0",
						"1"
					],
					"port": "8004",
					"path": [
						"favourites",
						"check",
						"4"
					]
				}
			},
			"response": []
		},
		{
			"name": "Remove from favs",
			"request": {
				"method": "DELETE",
				"header": [],
				"url": {
					"raw": "http://127.0.0.1:8004/favourites/6",
					"protocol": "http",
					"host": [
						"127",
						"0",
						"0",
						"1"
					],
					"port": "8004",
					"path": [
						"favourites",
						"6"
					]
				}
			},
			"response": []
		}
	],
	"auth": {
		"type": "apikey",
		"apikey": [
			{
				"key": "value",
				"value": "{{auth-token}}",
				"type": "string"
			},
			{
				"key": "key",
				"value": "Authorization",
				"type": "string"
			}
		]
	},
	"event": [
		{
			"listen": "prerequest",
			"script": {
				"type": "text/javascript",
				"exec": [
					""
				]
			}
		},
		{
			"listen": "test",
			"script": {
				"type": "text/javascript",
				"exec": [
					""
				]
			}
		}
	]
}